dreadnode/__init__.py
dreadnode/__main__.py
dreadnode/common_types.py
dreadnode/constants.py
dreadnode/convert.py
dreadnode/discovery.py
dreadnode/error.py
dreadnode/exporter.py
dreadnode/format.py
dreadnode/logging_.py
dreadnode/main.py
dreadnode/metric.py
dreadnode/object.py
dreadnode/py.typed
dreadnode/serialization.py
dreadnode/task.py
dreadnode/user_config.py
dreadnode/util.py
dreadnode/version.py
dreadnode/agent/__init__.py
dreadnode/agent/agent.py
dreadnode/agent/error.py
dreadnode/agent/events.py
dreadnode/agent/format.py
dreadnode/agent/reactions.py
dreadnode/agent/result.py
dreadnode/agent/stop.py
dreadnode/agent/thread.py
dreadnode/agent/hooks/__init__.py
dreadnode/agent/hooks/backoff.py
dreadnode/agent/hooks/base.py
dreadnode/agent/hooks/metrics.py
dreadnode/agent/hooks/summarize.py
dreadnode/agent/prompts/__init__.py
dreadnode/agent/prompts/summarize.py
dreadnode/agent/tools/__init__.py
dreadnode/agent/tools/base.py
dreadnode/agent/tools/execute.py
dreadnode/agent/tools/fs.py
dreadnode/agent/tools/memory.py
dreadnode/agent/tools/planning.py
dreadnode/agent/tools/reporting.py
dreadnode/agent/tools/tasking.py
dreadnode/airt/__init__.py
dreadnode/airt/attack/__init__.py
dreadnode/airt/attack/base.py
dreadnode/airt/attack/crescendo.py
dreadnode/airt/attack/goat.py
dreadnode/airt/attack/hop_skip_jump.py
dreadnode/airt/attack/nes.py
dreadnode/airt/attack/prompt.py
dreadnode/airt/attack/simba.py
dreadnode/airt/attack/tap.py
dreadnode/airt/attack/zoo.py
dreadnode/airt/search/__init__.py
dreadnode/airt/search/hop_skip_jump.py
dreadnode/airt/search/image_utils.py
dreadnode/airt/search/nes.py
dreadnode/airt/search/simba.py
dreadnode/airt/search/zoo.py
dreadnode/airt/target/__init__.py
dreadnode/airt/target/base.py
dreadnode/airt/target/custom.py
dreadnode/airt/target/llm.py
dreadnode/api/__init__.py
dreadnode/api/client.py
dreadnode/api/models.py
dreadnode/api/util.py
dreadnode/artifact/__init__.py
dreadnode/artifact/credential_manager.py
dreadnode-1.17.1.dist-info/METADATA
dreadnode-1.17.1.dist-info/WHEEL
dreadnode-1.17.1.dist-info/entry_points.txt
dreadnode-1.17.1.dist-info/licenses/LICENSE
dreadnode-1.17.1.dist-info/RECORD
