Metadata-Version: 2.4
Name: dreadnode
Version: 1.17.1
Summary: Dreadnode SDK
Project-URL: Homepage, https://github.com/dreadnode/sdk
Project-URL: Repository, https://github.com/dreadnode/sdk
Project-URL: Documentation, https://docs.dreadnode.io
Author-email: Nick Landers <monoxgas@gmail.com>
License:                                  Apache License
License-File: LICENSE
Classifier: License :: OSI Approved :: Apache Software License
Classifier: Operating System :: OS Independent
Classifier: Programming Language :: Python :: 3
Classifier: Programming Language :: Python :: 3.10
Classifier: Programming Language :: Python :: 3.11
Classifier: Programming Language :: Python :: 3.12
Classifier: Programming Language :: Python :: 3.13
Requires-Python: <3.14,>=3.10
Requires-Dist: aiofiles<25.0.0,>=24.1.0
Requires-Dist: coolname<3.0.0,>=2.2.0
Requires-Dist: cyclopts>=4.2.0
Requires-Dist: fsspec[s3]<=2025.12.0,>=2023.1.0
Requires-Dist: httpx<1.0.0,>=0.28.0
Requires-Dist: logfire<=3.20.0,>=3.5.3
Requires-Dist: loguru>=0.7.3
Requires-Dist: numpy<=2.3.5
Requires-Dist: optuna<5.0.0,>=4.5.0
Requires-Dist: pandas<3.0.0,>=2.2.3
Requires-Dist: pydantic<3.0.0,>=2.9.2
Requires-Dist: python-jsonpath>=2.0.1
Requires-Dist: python-ulid<4.0.0,>=3.0.0
Requires-Dist: pyyaml>=6.0.2
Requires-Dist: rigging>=3.3.4
Requires-Dist: universal-pathlib<0.4.0,>=0.3.3
Provides-Extra: all
Requires-Dist: confusables<2.0.0,>=1.2.0; extra == 'all'
Requires-Dist: datasets<5.0.0,>=4.0.0; extra == 'all'
Requires-Dist: moviepy<3.0.0,>=2.1.2; extra == 'all'
Requires-Dist: nltk<4.0.0,>=3.9.1; extra == 'all'
Requires-Dist: pillow<12.0.0,>=11.2.1; extra == 'all'
Requires-Dist: presidio-analyzer<3.0.0,>=2.2.359; extra == 'all'
Requires-Dist: pyarrow<22.1.0,>=22.0.0; extra == 'all'
Requires-Dist: rapidfuzz>=3.14.1; extra == 'all'
Requires-Dist: scikit-learn<2.0.0,>=1.7.1; extra == 'all'
Requires-Dist: sentence-transformers<6.0.0,>=5.1.0; extra == 'all'
Requires-Dist: soundfile<1.0.0,>=0.13.1; extra == 'all'
Requires-Dist: textblob<1.0.0,>=0.19.0; extra == 'all'
Requires-Dist: textstat<1.0.0,>=0.7.10; extra == 'all'
Requires-Dist: transformers<5.0.0,>=4.41.0; extra == 'all'
Provides-Extra: multimodal
Requires-Dist: moviepy<3.0.0,>=2.1.2; extra == 'multimodal'
Requires-Dist: pillow<12.0.0,>=11.2.1; extra == 'multimodal'
Requires-Dist: soundfile<1.0.0,>=0.13.1; extra == 'multimodal'
Provides-Extra: scoring
Requires-Dist: confusables<2.0.0,>=1.2.0; extra == 'scoring'
Requires-Dist: nltk<4.0.0,>=3.9.1; extra == 'scoring'
Requires-Dist: presidio-analyzer<3.0.0,>=2.2.359; extra == 'scoring'
Requires-Dist: rapidfuzz>=3.14.1; extra == 'scoring'
Requires-Dist: scikit-learn<2.0.0,>=1.7.1; extra == 'scoring'
Requires-Dist: sentence-transformers<6.0.0,>=5.1.0; extra == 'scoring'
Requires-Dist: textblob<1.0.0,>=0.19.0; extra == 'scoring'
Requires-Dist: textstat<1.0.0,>=0.7.10; extra == 'scoring'
Provides-Extra: training
Requires-Dist: datasets<5.0.0,>=4.0.0; extra == 'training'
Requires-Dist: pyarrow<22.1.0,>=22.0.0; extra == 'training'
Requires-Dist: transformers<5.0.0,>=4.41.0; extra == 'training'
Provides-Extra: transforms
Requires-Dist: art<7.0.0,>=6.5; extra == 'transforms'
